pycona/__init__.py
pycona/metrics.py
pycona/utils.py
pycona/active_algorithms/__init__.py
pycona/active_algorithms/algorithm_core.py
pycona/active_algorithms/genacq.py
pycona/active_algorithms/growacq.py
pycona/active_algorithms/mineacq.py
pycona/active_algorithms/mquacq.py
pycona/active_algorithms/mquacq2.py
pycona/active_algorithms/pquacq.py
pycona/active_algorithms/quacq.py
pycona/active_algorithms/utils.py
pycona/answering_queries/__init__.py
pycona/answering_queries/constraint_oracle.py
pycona/answering_queries/oracle.py
pycona/answering_queries/user_oracle.py
pycona/benchmarks/__init__.py
pycona/benchmarks/exam_timetabling.py
pycona/benchmarks/golomb.py
pycona/benchmarks/job_shop_scheduling.py
pycona/benchmarks/jsudoku.py
pycona/benchmarks/murder.py
pycona/benchmarks/nqueens.py
pycona/benchmarks/nurse_rostering.py
pycona/benchmarks/sudoku.py
pycona/benchmarks/zebra.py
pycona/ca_environment/__init__.py
pycona/ca_environment/acive_ca_proba.py
pycona/ca_environment/active_ca.py
pycona/ca_environment/ca_env_core.py
pycona/find_constraint/__init__.py
pycona/find_constraint/findc.py
pycona/find_constraint/findc2.py
pycona/find_constraint/findc_core.py
pycona/find_constraint/findc_obj.py
pycona/find_constraint/utils.py
pycona/find_scope/__init__.py
pycona/find_scope/findscope.py
pycona/find_scope/findscope2.py
pycona/find_scope/findscope_core.py
pycona/find_scope/findscope_obj.py
pycona/predictor/__init__.py
pycona/predictor/feature_representation.py
pycona/predictor/predictor.py
pycona/problem_instance/__init__.py
pycona/problem_instance/language.py
pycona/problem_instance/problem_instance.py
pycona/problem_instance/utils.py
pycona/query_generation/__init__.py
pycona/query_generation/pqgen.py
pycona/query_generation/qgen.py
pycona/query_generation/qgen_core.py
pycona/query_generation/qgen_obj.py
pycona/query_generation/tqgen.py
pycona-0.4.1.dist-info/licenses/LICENSE
pycona-0.4.1.dist-info/METADATA
pycona-0.4.1.dist-info/WHEEL
pycona-0.4.1.dist-info/top_level.txt
pycona-0.4.1.dist-info/RECORD
